vedika/__init__.py
vedika/normalizer.py
vedika/sandhi_join.py
vedika/sandhi_split.py
vedika/sentence_splitter.py
vedika/syllabification.py
vedika/tokenizer.py
vedika-0.0.14.dist-info/licenses/LICENSE
vedika-0.0.14.dist-info/METADATA
vedika-0.0.14.dist-info/WHEEL
vedika-0.0.14.dist-info/top_level.txt
vedika-0.0.14.dist-info/RECORD
