Metadata-Version: 2.4
Name: vedika
Version: 0.0.14
Summary: A comprehensive toolkit for Sanskrit text processing
Home-page: https://github.com/tanuj437/Vedika
Author: Tanuj Saxena and Soumya Sharma
Author-email: Tanuj Saxena <tanuj.saxena.rks@gmail.com>, Soumya Sharma <soumyasharma1599@gmail.com>
License-Expression: MIT
Keywords: Sanskrit,SanskritNLP,Sanskrit Toolkit,Toolkit
Requires-Python: >=3.8
License-File: LICENSE
Requires-Dist: torch>=1.9.0
Requires-Dist: numpy>=1.19.0
Requires-Dist: pandas>=1.3.0
Requires-Dist: tqdm>=4.62.0
Requires-Dist: regex>=2021.8.3
Requires-Dist: huggingface_hub>=0.22.2
Dynamic: license-file
